GraphFloris/WindFarm.py
GraphFloris/__init__.py
GraphFloris/config.py
GraphFloris/gen_graph.py
GraphFloris/layout_sampling.py
GraphFloris/visualize.py
examples/__init__.py
GraphFloris-0.20.dist-info/LICENSE
GraphFloris-0.20.dist-info/METADATA
GraphFloris-0.20.dist-info/WHEEL
GraphFloris-0.20.dist-info/top_level.txt
GraphFloris-0.20.dist-info/RECORD
