Metadata-Version: 2.1
Name: GraphFloris
Version: 0.20
Summary: Graph represented wind farm power simulator
Home-page: https://github.com/Junyoungpark/GraphFloris
Author: Junyoung Park
Author-email: Junyoungpark@kaist.com
License: UNKNOWN
Download-URL: https://github.com/Junyoungpark/GraphFloris
Keywords: floris,graph
Platform: UNKNOWN
Requires-Python: >=3
Requires-Dist: floris
Requires-Dist: torch
Requires-Dist: dgl
Requires-Dist: networkx
Requires-Dist: matplotlib
